trainsandtests/PCAA.py
trainsandtests/Reacting.py
trainsandtests/__init__.py
trainsandtests-0.2.0.dist-info/LICENSE.txt
trainsandtests-0.2.0.dist-info/METADATA
trainsandtests-0.2.0.dist-info/WHEEL
trainsandtests-0.2.0.dist-info/top_level.txt
trainsandtests-0.2.0.dist-info/RECORD
